{
  "version": 1,
  "objects": [
    {
      "id": "image-classifier-overview",
      "type": "dashboard",
      "attributes": {
        "title": "Image Classifier Logs Overview",
        "description": "Overview of image classifier application logs",
        "panelsJSON": "[{\"version\":\"7.0.0\",\"gridData\":{\"x\":0,\"y\":0,\"w\":24,\"h\":15,\"i\":\"1\"},\"panelIndex\":\"1\",\"embeddableConfig\":{},\"panelRefName\":\"panel_1\"},{\"version\":\"7.0.0\",\"gridData\":{\"x\":24,\"y\":0,\"w\":24,\"h\":15,\"i\":\"2\",\"panelIndex\":\"2\"},\"embeddableConfig\":{},\"panelRefName\":\"panel_2\"},{\"version\":\"7.0.0\",\"gridData\":{\"x\":0,\"y\":15,\"w\":48,\"h\":15,\"i\":\"3\",\"panelIndex\":\"3\"},\"embeddableConfig\":{},\"panelRefName\":\"panel_3\"}]",
        "optionsJSON": "{\"darkTheme\":false,\"useMargins\":true,\"syncColors\":false,\"hidePanelTitles\":false}",
        "version": 1,
        "timeRestore": false,
        "kibanaSavedObjectMeta": {
          "searchSourceJSON": "{\"query\":{\"query\":\"\",\"language\":\"kuery\"},\"filter\":[]}"
        }
      }
    },
    {
      "id": "log-level-distribution",
      "type": "visualization",
      "attributes": {
        "title": "Log Level Distribution",
        "visState": "{\"title\":\"Log Level Distribution\",\"type\":\"pie\",\"params\":{\"addTooltip\":true,\"addLegend\":true,\"legendPosition\":\"right\",\"isDonut\":true,\"labels\":{\"show\":false,\"values\":true,\"last_level\":true,\"truncate\":100}},\"aggs\":[{\"id\":\"1\",\"type\":\"count\",\"schema\":\"metric\",\"params\":{}},{\"id\":\"2\",\"type\":\"terms\",\"schema\":\"segment\",\"params\":{\"field\":\"level.keyword\",\"size\":5,\"order\":\"desc\",\"orderBy\":\"1\"}}]}",
        "uiStateJSON": "{}",
        "description": "Distribution of log levels",
        "version": 1,
        "kibanaSavedObjectMeta": {
          "searchSourceJSON": "{\"index\":\"image-classifier-logs-*\",\"query\":{\"match_all\":{}},\"filter\":[]}"
        }
      }
    },
    {
      "id": "request-timeline",
      "type": "visualization",
      "attributes": {
        "title": "Request Timeline",
        "visState": "{\"title\":\"Request Timeline\",\"type\":\"histogram\",\"params\":{\"grid\":{\"categoryLines\":false,\"style\":{\"color\":\"#eee\"}},\"categoryAxes\":[{\"id\":\"CategoryAxis-1\",\"type\":\"category\",\"position\":\"bottom\",\"show\":true,\"style\":{},\"scale\":{\"type\":\"linear\"},\"labels\":{\"show\":true,\"truncate\":100},\"title\":{}}],\"valueAxes\":[{\"id\":\"ValueAxis-1\",\"name\":\"LeftAxis-1\",\"type\":\"value\",\"position\":\"left\",\"show\":true,\"style\":{},\"scale\":{\"type\":\"linear\",\"mode\":\"normal\"},\"labels\":{\"show\":true,\"rotate\":0,\"filter\":false,\"truncate\":100},\"title\":{\"text\":\"Count\"}}],\"seriesParams\":[{\"show\":true,\"type\":\"histogram\",\"mode\":\"stacked\",\"data\":{\"label\":\"Count\",\"id\":\"1\"},\"valueAxis\":\"ValueAxis-1\",\"drawLinesBetweenPoints\":true,\"showCircles\":true}],\"addTooltip\":true,\"addLegend\":true,\"legendPosition\":\"right\",\"times\":[],\"addTimeMarker\":false},\"aggs\":[{\"id\":\"1\",\"type\":\"count\",\"schema\":\"metric\",\"params\":{}},{\"id\":\"2\",\"type\":\"date_histogram\",\"schema\":\"segment\",\"params\":{\"field\":\"@timestamp\",\"interval\":\"auto\",\"customInterval\":\"2h\",\"min_doc_count\":1,\"extended_bounds\":{}}}]}",
        "uiStateJSON": "{}",
        "description": "Timeline of requests over time",
        "version": 1,
        "kibanaSavedObjectMeta": {
          "searchSourceJSON": "{\"index\":\"image-classifier-logs-*\",\"query\":{\"bool\":{\"must\":[{\"match\":{\"request_type\":\"api\"}}]}},\"filter\":[]}"
        }
      }
    },
    {
      "id": "error-analysis",
      "type": "visualization",
      "attributes": {
        "title": "Error Analysis",
        "visState": "{\"title\":\"Error Analysis\",\"type\":\"table\",\"params\":{\"perPage\":10,\"showPartialRows\":false,\"showMeticsAtAllLevels\":false,\"sort\":{\"columnIndex\":null,\"direction\":null},\"showTotal\":false,\"showToolbar\":true,\"totalFunc\":\"sum\"},\"aggs\":[{\"id\":\"1\",\"type\":\"count\",\"schema\":\"metric\",\"params\":{}},{\"id\":\"2\",\"type\":\"terms\",\"schema\":\"bucket\",\"params\":{\"field\":\"error_type.keyword\",\"size\":10,\"order\":\"desc\",\"orderBy\":\"1\"}},{\"id\":\"3\",\"type\":\"terms\",\"schema\":\"bucket\",\"params\":{\"field\":\"endpoint.keyword\",\"size\":10,\"order\":\"desc\",\"orderBy\":\"1\"}}]}",
        "uiStateJSON": "{}",
        "description": "Analysis of errors by type and endpoint",
        "version": 1,
        "kibanaSavedObjectMeta": {
          "searchSourceJSON": "{\"index\":\"image-classifier-logs-*\",\"query\":{\"bool\":{\"must\":[{\"match\":{\"level\":\"ERROR\"}}]}},\"filter\":[]}"
        }
      }
    }
  ]
}
